aab_service.py
prompts/__init__.py
prompts/breadcrumbs.py
prompts/constants.py
prompts/expressions.py
prompts/menu_navigations.py
prompts/objects_fields.py
prompts/page_planner.py
prompts/pages.py
prompts/planner.py
prompts/router.py
prompts/solutions_applications.py
prompts/view_filter_planner.py
prompts/view_links_planner.py
prompts/view_planner.py
prompts/views.py
aab_prompts-1.1.5.dist-info/METADATA
aab_prompts-1.1.5.dist-info/WHEEL
aab_prompts-1.1.5.dist-info/top_level.txt
aab_prompts-1.1.5.dist-info/RECORD
